alibabacloud_schedulerx320240624/__init__.py
alibabacloud_schedulerx320240624/client.py
alibabacloud_schedulerx320240624/models/__init__.py
alibabacloud_schedulerx320240624/models/_create_app_request.py
alibabacloud_schedulerx320240624/models/_create_app_response.py
alibabacloud_schedulerx320240624/models/_create_app_response_body.py
alibabacloud_schedulerx320240624/models/_create_calendar_request.py
alibabacloud_schedulerx320240624/models/_create_calendar_response.py
alibabacloud_schedulerx320240624/models/_create_calendar_response_body.py
alibabacloud_schedulerx320240624/models/_create_cluster_request.py
alibabacloud_schedulerx320240624/models/_create_cluster_response.py
alibabacloud_schedulerx320240624/models/_create_cluster_response_body.py
alibabacloud_schedulerx320240624/models/_create_cluster_shrink_request.py
alibabacloud_schedulerx320240624/models/_create_executors_request.py
alibabacloud_schedulerx320240624/models/_create_executors_response.py
alibabacloud_schedulerx320240624/models/_create_executors_response_body.py
alibabacloud_schedulerx320240624/models/_create_job_request.py
alibabacloud_schedulerx320240624/models/_create_job_response.py
alibabacloud_schedulerx320240624/models/_create_job_response_body.py
alibabacloud_schedulerx320240624/models/_create_job_shrink_request.py
alibabacloud_schedulerx320240624/models/_create_workflow_request.py
alibabacloud_schedulerx320240624/models/_create_workflow_response.py
alibabacloud_schedulerx320240624/models/_create_workflow_response_body.py
alibabacloud_schedulerx320240624/models/_delete_app_request.py
alibabacloud_schedulerx320240624/models/_delete_app_response.py
alibabacloud_schedulerx320240624/models/_delete_app_response_body.py
alibabacloud_schedulerx320240624/models/_delete_calendar_request.py
alibabacloud_schedulerx320240624/models/_delete_calendar_response.py
alibabacloud_schedulerx320240624/models/_delete_calendar_response_body.py
alibabacloud_schedulerx320240624/models/_delete_cluster_request.py
alibabacloud_schedulerx320240624-1.5.0.dist-info/LICENSE
alibabacloud_schedulerx320240624-1.5.0.dist-info/METADATA
alibabacloud_schedulerx320240624-1.5.0.dist-info/WHEEL
alibabacloud_schedulerx320240624-1.5.0.dist-info/top_level.txt
alibabacloud_schedulerx320240624-1.5.0.dist-info/RECORD
